dwhlogs/__init__.py
dwhlogs/function.py
dwhlogs/main.py
nolk_dwh-0.0.7.dist-info/METADATA
nolk_dwh-0.0.7.dist-info/WHEEL
nolk_dwh-0.0.7.dist-info/top_level.txt
nolk_dwh-0.0.7.dist-info/RECORD
