Metadata-Version: 2.1
Name: nolk-dwh
Version: 0.0.7
Requires-Dist: requests
Requires-Dist: importlib ; python_version == "3.8"
